AUTHORS.rst
CONTRIBUTING.rst
HISTORY.rst
LICENSE
MANIFEST.in
README.rst
setup.cfg
setup.py
code_cleaner.egg-info/PKG-INFO
code_cleaner.egg-info/SOURCES.txt
code_cleaner.egg-info/dependency_links.txt
code_cleaner.egg-info/not-zip-safe
code_cleaner.egg-info/top_level.txt
codecleaner/__init__.py
codecleaner/cleaner.py
codecleaner/codecleaner.py
codecleaner/pipeline.py
docs/Makefile
docs/authors.rst
docs/conf.py
docs/contributing.rst
docs/history.rst
docs/index.rst
docs/installation.rst
docs/make.bat
docs/readme.rst
docs/usage.rst
tests/__init__.py
tests/test_codecleaner.py
tests/samples/comments_1_clean.txt
tests/samples/comments_1_original.txt
tests/samples/documentation_1_clean.txt
tests/samples/documentation_1_original.txt