Metadata-Version: 1.2
Name: code-cleaner
Version: 0.1.9
Summary: A library for text preprocessing of source code. The library offers a simple interface, and supports multiple programming languages
Home-page: https://github.com/SasCezar/code-cleaner
Author: Cezar Sas
Author-email: cezar.sas@gmail.com
License: GNU General Public License v3
Keywords: code-cleaner
Platform: UNKNOWN
Classifier: Development Status :: 2 - Pre-Alpha
Classifier: Intended Audience :: Developers
Classifier: License :: OSI Approved :: GNU General Public License v3 (GPLv3)
Classifier: Natural Language :: English
Classifier: Programming Language :: Python :: 3
Classifier: Programming Language :: Python :: 3.5
Classifier: Programming Language :: Python :: 3.6
Classifier: Programming Language :: Python :: 3.7
Classifier: Programming Language :: Python :: 3.8
Requires-Python: >=3.5
